jihyocrypt/README.md
jihyocrypt/__init__.py
jihyocrypt/__main__.py
jihyocrypt/getpass.py
jihyocrypt/password_generators.py
jihyocrypt/setup.py
jihyocrypt-2.5.0.5.dist-info/METADATA
jihyocrypt-2.5.0.5.dist-info/WHEEL
jihyocrypt-2.5.0.5.dist-info/top_level.txt
jihyocrypt-2.5.0.5.dist-info/RECORD
