Metadata-Version: 2.1
Name: jihyocrypt
Version: 2.5.0.5
Summary: A simple implementation of Salsa20 along with a nonce+password based key and hash determination function.     Multiple exposed functions to ease encryption and decryption to a single key based program. 
Home-page: https://gitlab.com/loggerheads-with-binary/jihyocrypt/
Author: Anna Aniruddh Radhakrishnan
Author-email: dev@aniruddh.ml
License: UNKNOWN
Download-URL: http://pypi.python.org/pypi/jihyocrypt
Project-URL: Documentation, https://gitlab.com/loggerheads-with-binary/jihyocrypt/README.md
Project-URL: Source, https://gitlab.com/loggerheads-with-binary/jihyocrypt/
Project-URL: Tracker, https://gitlab.com/loggerheads-with-binary/jihyocrypt/issues
Platform: UNKNOWN
Classifier: Operating System :: OS Independent
Classifier: Environment :: Console
Classifier: Intended Audience :: Developers
Classifier: Intended Audience :: System Administrators
Classifier: License :: OSI Approved :: MIT License
Classifier: Programming Language :: Python :: 3
Classifier: Natural Language :: English
Classifier: Topic :: Security :: Cryptography
Requires-Dist: pycryptodome
